{"results": {"test": [{"loss": 0.555535385131836, "accuracy": 91.84}, {"loss": 0.5126185470581055, "accuracy": 92.73}], "test_counterfactual": [{"loss": 0.5682232940673828, "accuracy": 92.06}, {"loss": 0.6015021759033203, "accuracy": 92.26}], "test_counterfactual_rot": [{"loss": 10.43885478515625, "accuracy": 21.72}, {"loss": 13.269512939453126, "accuracy": 21.35}], "test_counterfactual_rot_scale": [{"loss": 11.8096017578125, "accuracy": 19.21}, {"loss": 14.134976904296876, "accuracy": 19.55}], "test_counterfactual_rot_scale_shear": [{"loss": 11.919673095703125, "accuracy": 18.24}, {"loss": 14.517791259765625, "accuracy": 18.58}], "test_counterfactual_scale": [{"loss": 2.0365929565429686, "accuracy": 69.6}, {"loss": 2.417774334716797, "accuracy": 69.77}], "train": [{"loss": 0.02456851489841938, "accuracy": 96.5817}, {"loss": 0.06433242559432983, "accuracy": 98.3908}]}, "train_len": 1000000, "test_len": 10000, "dataset": "double_colored_MNIST_counterfactual", "num_params": 619285.0}